{
  "id": "ed6c3ad6-5ac8-4786-8773-6833fe0e1476",
  "prevId": "7ef0e5b7-278e-4341-acdc-7fc9bf4a786c",
  "version": "7",
  "dialect": "postgresql",
  "tables": {
    "public.tb_financial": {
      "name": "tb_financial",
      "schema": "",
      "columns": {
        "id": {
          "name": "id",
          "type": "uuid",
          "primaryKey": true,
          "notNull": true,
          "default": "gen_random_uuid()"
        },
        "user_id": {
          "name": "user_id",
          "type": "uuid",
          "primaryKey": false,
          "notNull": true
        },
        "monthly_fee_value": {
          "name": "monthly_fee_value",
          "type": "integer",
          "primaryKey": false,
          "notNull": true
        },
        "due_date": {
          "name": "due_date",
          "type": "integer",
          "primaryKey": false,
          "notNull": true
        },
        "paid": {
          "name": "paid",
          "type": "boolean",
          "primaryKey": false,
          "notNull": true,
          "default": false
        },
        "updated_at": {
          "name": "updated_at",
          "type": "date",
          "primaryKey": false,
          "notNull": true,
          "default": "now()"
        },
        "created_at": {
          "name": "created_at",
          "type": "date",
          "primaryKey": false,
          "notNull": true,
          "default": "now()"
        }
      },
      "indexes": {},
      "foreignKeys": {
        "tb_financial_user_id_tb_users_id_fk": {
          "name": "tb_financial_user_id_tb_users_id_fk",
          "tableFrom": "tb_financial",
          "tableTo": "tb_users",
          "columnsFrom": [
            "user_id"
          ],
          "columnsTo": [
            "id"
          ],
          "onDelete": "no action",
          "onUpdate": "no action"
        }
      },
      "compositePrimaryKeys": {},
      "uniqueConstraints": {},
      "policies": {},
      "checkConstraints": {},
      "isRLSEnabled": false
    },
    "public.tb_health_metrics": {
      "name": "tb_health_metrics",
      "schema": "",
      "columns": {
        "id": {
          "name": "id",
          "type": "uuid",
          "primaryKey": true,
          "notNull": true,
          "default": "gen_random_uuid()"
        },
        "user_id": {
          "name": "user_id",
          "type": "uuid",
          "primaryKey": false,
          "notNull": true
        },
        "height_cm": {
          "name": "height_cm",
          "type": "varchar(5)",
          "primaryKey": false,
          "notNull": true
        },
        "weight_kg": {
          "name": "weight_kg",
          "type": "varchar(5)",
          "primaryKey": false,
          "notNull": true
        },
        "blood_type": {
          "name": "blood_type",
          "type": "varchar(3)",
          "primaryKey": false,
          "notNull": true
        },
        "has_practiced_sports": {
          "name": "has_practiced_sports",
          "type": "boolean",
          "primaryKey": false,
          "notNull": true
        },
        "last_exercise": {
          "name": "last_exercise",
          "type": "text",
          "primaryKey": false,
          "notNull": true
        },
        "history_diseases": {
          "name": "history_diseases",
          "type": "text",
          "primaryKey": false,
          "notNull": true
        },
        "medications": {
          "name": "medications",
          "type": "text",
          "primaryKey": false,
          "notNull": true
        },
        "sports_history": {
          "name": "sports_history",
          "type": "text",
          "primaryKey": false,
          "notNull": true
        },
        "allergies": {
          "name": "allergies",
          "type": "text",
          "primaryKey": false,
          "notNull": true
        },
        "injuries": {
          "name": "injuries",
          "type": "text",
          "primaryKey": false,
          "notNull": true
        },
        "updated_at": {
          "name": "updated_at",
          "type": "date",
          "primaryKey": false,
          "notNull": true,
          "default": "now()"
        },
        "alimental_routine": {
          "name": "alimental_routine",
          "type": "text",
          "primaryKey": false,
          "notNull": true
        },
        "diary_routine": {
          "name": "diary_routine",
          "type": "text",
          "primaryKey": false,
          "notNull": true
        },
        "use_supplements": {
          "name": "use_supplements",
          "type": "boolean",
          "primaryKey": false,
          "notNull": true
        },
        "what_supplements": {
          "name": "what_supplements",
          "type": "text",
          "primaryKey": false,
          "notNull": false
        },
        "other_notes": {
          "name": "other_notes",
          "type": "text",
          "primaryKey": false,
          "notNull": false
        },
        "coach_observations": {
          "name": "coach_observations",
          "type": "text",
          "primaryKey": false,
          "notNull": false
        }
      },
      "indexes": {},
      "foreignKeys": {
        "tb_health_metrics_user_id_tb_users_id_fk": {
          "name": "tb_health_metrics_user_id_tb_users_id_fk",
          "tableFrom": "tb_health_metrics",
          "tableTo": "tb_users",
          "columnsFrom": [
            "user_id"
          ],
          "columnsTo": [
            "id"
          ],
          "onDelete": "no action",
          "onUpdate": "no action"
        }
      },
      "compositePrimaryKeys": {},
      "uniqueConstraints": {
        "tb_health_metrics_user_id_unique": {
          "name": "tb_health_metrics_user_id_unique",
          "nullsNotDistinct": false,
          "columns": [
            "user_id"
          ]
        }
      },
      "policies": {},
      "checkConstraints": {},
      "isRLSEnabled": false
    },
    "public.tb_personal_data": {
      "name": "tb_personal_data",
      "schema": "",
      "columns": {
        "id": {
          "name": "id",
          "type": "uuid",
          "primaryKey": true,
          "notNull": true,
          "default": "gen_random_uuid()"
        },
        "user_id": {
          "name": "user_id",
          "type": "uuid",
          "primaryKey": false,
          "notNull": true
        },
        "cpf": {
          "name": "cpf",
          "type": "varchar(11)",
          "primaryKey": false,
          "notNull": true
        },
        "born_date": {
          "name": "born_date",
          "type": "date",
          "primaryKey": false,
          "notNull": true
        },
        "address": {
          "name": "address",
          "type": "text",
          "primaryKey": false,
          "notNull": true
        },
        "telephone": {
          "name": "telephone",
          "type": "text",
          "primaryKey": false,
          "notNull": true
        }
      },
      "indexes": {},
      "foreignKeys": {
        "tb_personal_data_user_id_tb_users_id_fk": {
          "name": "tb_personal_data_user_id_tb_users_id_fk",
          "tableFrom": "tb_personal_data",
          "tableTo": "tb_users",
          "columnsFrom": [
            "user_id"
          ],
          "columnsTo": [
            "id"
          ],
          "onDelete": "no action",
          "onUpdate": "no action"
        }
      },
      "compositePrimaryKeys": {},
      "uniqueConstraints": {
        "tb_personal_data_user_id_unique": {
          "name": "tb_personal_data_user_id_unique",
          "nullsNotDistinct": false,
          "columns": [
            "user_id"
          ]
        },
        "tb_personal_data_cpf_unique": {
          "name": "tb_personal_data_cpf_unique",
          "nullsNotDistinct": false,
          "columns": [
            "cpf"
          ]
        }
      },
      "policies": {},
      "checkConstraints": {},
      "isRLSEnabled": false
    },
    "public.tb_users": {
      "name": "tb_users",
      "schema": "",
      "columns": {
        "id": {
          "name": "id",
          "type": "uuid",
          "primaryKey": true,
          "notNull": true,
          "default": "gen_random_uuid()"
        },
        "name": {
          "name": "name",
          "type": "text",
          "primaryKey": false,
          "notNull": true
        },
        "created_at": {
          "name": "created_at",
          "type": "date",
          "primaryKey": false,
          "notNull": true,
          "default": "now()"
        }
      },
      "indexes": {},
      "foreignKeys": {},
      "compositePrimaryKeys": {},
      "uniqueConstraints": {},
      "policies": {},
      "checkConstraints": {},
      "isRLSEnabled": false
    }
  },
  "enums": {},
  "schemas": {},
  "sequences": {},
  "roles": {},
  "policies": {},
  "views": {},
  "_meta": {
    "columns": {},
    "schemas": {},
    "tables": {}
  }
}